{
  "bug_prediction_metrics": [
    {
      "name": "LOC-ADDED",
      "category": "process metric",
      "is_novel": false,
      "description": "N/A"
    },
    {
      "name": "LOC-DELETED",
      "category": "process metric",
      "is_novel": false,
      "description": "N/A"
    },
    {
      "name": "LOC-CHANGED",
      "category": "process metric",
      "is_novel": false,
      "description": "N/A"
    },
    {
      "name": "MAX-LOC-ADDED",
      "category": "process metric",
      "is_novel": false,
      "description": "N/A"
    },
    {
      "name": "MAX_LOC-CHANGED",
      "category": "process metric",
      "is_novel": false,
      "description": "N/A"
    },
    {
      "name": "MAX_LOC_DELETED",
      "category": "process metric",
      "is_novel": false,
      "description": "N/A"
    },
    {
      "name": "CODE CHURN",
      "category": "process metric",
      "is_novel": false,
      "description": "N/A"
    },
    {
      "name": "MAX CODE CHURN",
      "category": "process metric",
      "is_novel": false,
      "description": "N/A"
    },
    {
      "name": "AVERAGE CODE CHURN",
      "category": "process metric",
      "is_novel": false,
      "description": "N/A"
    }
  ],
  "source_locations": {
    "bug_prediction_metrics": "Section 3.1, Page 421"
  }
}